README.rst
setup.py
txgeonames/__init__.py
txgeonames/client.py
txgeonames/interface.py
txgeonames.egg-info/PKG-INFO
txgeonames.egg-info/SOURCES.txt
txgeonames.egg-info/dependency_links.txt
txgeonames.egg-info/requires.txt
txgeonames.egg-info/top_level.txt
txgeonames/test/__init__.py
txgeonames/test/test_client.py