Metadata-Version: 1.1
Name: txgeonames
Version: 20121106
Summary: Twisted client for the GeoNames API
Home-page: https://github.com/lvh/txgeonames
Author: Laurens Van Houtven
Author-email: _@lvh.cc
License: ISC
Platform: UNKNOWN
Classifier: Development Status :: 3 - Alpha
Classifier: Framework :: Twisted
Classifier: License :: OSI Approved :: ISC License (ISCL)
